fr-stubs/__init__.pyi
fr-stubs/cnes/__init__.pyi
fr-stubs/cnes/sirius/__init__.pyi
fr-stubs/cnes/sirius/addons/__init__.pyi
fr-stubs/cnes/sirius/addons/patriusdataset/__init__.pyi
fr-stubs/cnes/sirius/addons/patriusdataset/atmosphere/__init__.pyi
fr-stubs/cnes/sirius/addons/patriusdataset/ephemerides/__init__.pyi
fr-stubs/cnes/sirius/addons/patriusdataset/force-models/__init__.pyi
fr-stubs/cnes/sirius/addons/patriusdataset/force-models/potential/__init__.pyi
fr-stubs/cnes/sirius/patrius/__init__.pyi
fr-stubs/cnes/sirius/patrius/assembly/__init__.pyi
fr-stubs/cnes/sirius/patrius/assembly/models/__init__.pyi
fr-stubs/cnes/sirius/patrius/assembly/models/aerocoeffs/__init__.pyi
fr-stubs/cnes/sirius/patrius/assembly/models/cook/__init__.pyi
fr-stubs/cnes/sirius/patrius/assembly/properties/__init__.pyi
fr-stubs/cnes/sirius/patrius/assembly/properties/features/__init__.pyi
fr-stubs/cnes/sirius/patrius/assembly/vehicle/__init__.pyi
fr-stubs/cnes/sirius/patrius/attitudes/__init__.pyi
fr-stubs/cnes/sirius/patrius/attitudes/directions/__init__.pyi
fr-stubs/cnes/sirius/patrius/attitudes/kinematics/__init__.pyi
fr-stubs/cnes/sirius/patrius/attitudes/multi/__init__.pyi
fr-stubs/cnes/sirius/patrius/attitudes/orientations/__init__.pyi
fr-stubs/cnes/sirius/patrius/attitudes/profiles/__init__.pyi
fr-stubs/cnes/sirius/patrius/attitudes/slew/__init__.pyi
fr-stubs/cnes/sirius/patrius/bodies/__init__.pyi
fr-stubs/cnes/sirius/patrius/bodies/bsp/__init__.pyi
fr-stubs/cnes/sirius/patrius/bodies/bsp/spice/__init__.pyi
fr-stubs/cnes/sirius/patrius/bodies/mesh/__init__.pyi
fr-stubs/cnes/sirius/patrius/covariance/__init__.pyi
fr-stubs/cnes/sirius/patrius/data/__init__.pyi
fr-stubs/cnes/sirius/patrius/events/__init__.pyi
fr-stubs/cnes/sirius/patrius/events/detectors/__init__.pyi
fr-stubs/cnes/sirius/patrius/events/postprocessing/__init__.pyi
fr-stubs/cnes/sirius/patrius/events/utils/__init__.pyi
fr-stubs/cnes/sirius/patrius/fieldsofview/__init__.pyi
pytrius-0.1.2.dist-info/METADATA
pytrius-0.1.2.dist-info/WHEEL
pytrius-0.1.2.dist-info/licenses/LICENCE.txt
pytrius-0.1.2.dist-info/RECORD
