Metadata-Version: 2.4
Name: pytrius
Version: 0.1.2
Summary: This is a jpype wrapping of the original PATRIUS java code.
Project-URL: source, https://github.com/CNES/patrius
Project-URL: homepage, https://patrius.cnes.fr/index.php/Accueil
Author-email: Cloe Alcaria <cloe.alcaria@cnes.fr>
License: License :: OSI Approved :: Apache Software License
License-File: LICENCE.txt
Classifier: Operating System :: OS Independent
Classifier: Programming Language :: Python :: 3
Classifier: Programming Language :: Python :: 3.6
Classifier: Programming Language :: Python :: 3.7
Classifier: Programming Language :: Python :: 3.8
Classifier: Programming Language :: Python :: 3.9
Classifier: Programming Language :: Python :: 3.10
Classifier: Programming Language :: Python :: 3.11
Classifier: Programming Language :: Python :: 3.12
Classifier: Topic :: Scientific/Engineering
Requires-Python: >=3.6
Requires-Dist: jpype1
Requires-Dist: numpy
Provides-Extra: tests
Requires-Dist: coverage; extra == 'tests'
Requires-Dist: pytest; extra == 'tests'
Requires-Dist: pytest-cov; extra == 'tests'
